MANIFEST.in
README.md
setup.py
gradle_bio/__init__.py
gradle_bio/__main__.py
gradle_bio/utils.py
gradle_bio.egg-info/PKG-INFO
gradle_bio.egg-info/SOURCES.txt
gradle_bio.egg-info/dependency_links.txt
gradle_bio.egg-info/top_level.txt