Metadata-Version: 2.1
Name: gradle-bio
Version: 0.1.0
Summary: Collection of Android project snippets and templates
Home-page: https://github.com/yourusername/gradle-bio
Author: Your Name
Author-email: your.email@example.com
Classifier: Programming Language :: Python :: 3
Classifier: License :: OSI Approved :: MIT License
Classifier: Operating System :: OS Independent
Requires-Python: >=3.6
